comparerr/__init__.py
comparerr/comparerr_pylint_message.py
comparerr/comparerr_pylint_reporter.py
comparerr/report_generator.py
comparerr/utils/__init__.py
comparerr/utils/comparerr_pylint_message.py
comparerr/utils/comparerr_pylint_reporter.py
comparerr-0.2.0.data/scripts/comparerr
comparerr-0.2.0.data/scripts/pylint2comparerr
comparerr-0.2.0.dist-info/LICENSE
comparerr-0.2.0.dist-info/METADATA
comparerr-0.2.0.dist-info/WHEEL
comparerr-0.2.0.dist-info/top_level.txt
comparerr-0.2.0.dist-info/RECORD
