Metadata-Version: 2.1
Name: comparerr
Version: 0.2.0
Summary: Comparerr is a tool which which analyzes two versions of python software versioned by git with pylint and shows you errors which you added and fixed.
Home-page: https://github.com/TomasKorbar/comparerr
Author: Tomas Korbar
Author-email: tomas.korb@seznam.cz
License: GPL3
Keywords: lint,testing,CI
Platform: UNKNOWN
Classifier: Development Status :: 4 - Beta
Classifier: Topic :: Software Development :: Debuggers
Classifier: Topic :: Software Development :: Quality Assurance
Classifier: Topic :: Software Development :: Testing
Classifier: License :: OSI Approved :: GNU General Public License v3 (GPLv3)
Requires-Python: >=3.7
Requires-Dist: GitPython (>=3)
Requires-Dist: pylint (>=2.3.1)
